nba_gateway/__init__.py
nba_gateway/nba_gateway.py
nba_gateway_pdenno-0.1.0.dist-info/METADATA
nba_gateway_pdenno-0.1.0.dist-info/WHEEL
nba_gateway_pdenno-0.1.0.dist-info/top_level.txt
nba_gateway_pdenno-0.1.0.dist-info/RECORD
